omnidiff/__init__.py
omnidiff/omnidiff.py
omnidiff/test_omnidiff.py
omnidiff-1.3.dist-info/LICENSE
omnidiff-1.3.dist-info/METADATA
omnidiff-1.3.dist-info/WHEEL
omnidiff-1.3.dist-info/top_level.txt
omnidiff-1.3.dist-info/RECORD
